{"Title":"Gosford Park","Year":"2001","Rated":"R","Released":"18 Jan 2002","Runtime":"137 min","Genre":"Drama, Mystery","Director":"Robert Altman","Writer":"Robert Altman (idea), Julian Fellowes, Bob Balaban (idea)","Actors":"Maggie Smith, Michael Gambon, Kristin Scott Thomas, Camilla Rutherford","Plot":"Set in the 1930s, the story takes place in an old-fashioned English country house where a weekend shooting party is underway. The story centers on the McCordle family, particularly the man of the house, William McCordle. Getting on in years, William has become benefactor to many of his relatives and friends. As the weekend goes on, secrets are revealed, and it seems everyone, above stairs and below, wants a piece of William and his money, but how far will they go to get it?","Language":"English","Country":"UK, USA, Italy","Awards":"Won 1 Oscar. Another 29 wins & 72 nominations.","Poster":"http://ia.media-imdb.com/images/M/MV5BMTYwNDA3NDY2M15BMl5BanBnXkFtZTYwMDE4NTQ5._V1_SX300.jpg","Metascore":"90","imdbRating":"7.3","imdbVotes":"62,457","imdbID":"tt0280707","Type":"movie","Response":"True"}